{"forum": {"content": "\u5168\u4e16\u754c\u7684\u5973\u751f\u65e9\u5b89\uff5e<br />\u4e0d\u4f86\u8ddf\u4e00\u96bb\u55ae\u8eab\u72d7\u8aaa\u65e9\u5b89\uff1f", "images": ["http://filestoresg1.beetalkmobile.com:8081/file/60103b262ed436f9f789b0c89fa845d6"], "urls": [], "title": "\u65e9\u5b89030"}, "threadStatus": 0, "regionId": 886, "barStatus": 0, "barId": 205, "postBy": {"utc": 1526683004000, "level": 5, "location": "\u6843\u5712\u5e02\u00b7\u53f0\u7063", "avatar": "http://filestoresg1.beetalkmobile.com:8081/file/4902145129341012807", "name": "\u5a01\u5a01"}, "id": 8516197}
