{"forum": {"content": "\u597d\u50b7\u4eba\u5594 \u55da\u55da", "images": ["http://filestoresg1.beetalkmobile.com:8081/file/61db05085205bb46ac66125fd7522f50"], "urls": [], "title": "\u4ed6\u8aaa\u6211\u662f\u4eba\u985e\uff1f\u9084\u4eba\u5996\uff1f"}, "threadStatus": 0, "regionId": 886, "barStatus": 0, "barId": 10, "postBy": {"utc": 1523440253000, "level": 3, "location": "\u53f0\u4e2d\u5e02\u00b7\u53f0\u7063", "avatar": "http://filestoresg1.beetalkmobile.com:8081/file/-1125811924753721969", "name": "\u9ece\u9ece"}, "id": 8182429}
