{"forum": {"content": "\u662f\u4e0d\u662f\u6c92\u6709\u7d55\u5c0d\u7684\u7570\u6027\u6200\u554a\uff1f", "images": ["http://filestoresg1.beetalkmobile.com:8081/file/4bd4079080ddbb2bd75c5951f4533757"], "urls": [], "title": "\u7570\u6027\u6200"}, "threadStatus": 1, "regionId": 886, "barStatus": 0, "barId": 20, "postBy": {"utc": 1528897248000, "level": 1, "location": "\u53f0\u7063", "avatar": "http://filestoresg1.beetalkmobile.com:8081/file/-2983198222723639869", "name": "\u7490\u7490"}, "id": 8732642}
