{"forum": {"content": "\u5404\u4f4d\u904e\u5f97\u5982\u4f55\u554a<br /><br />\u662f\u4e0d\u662f\u9084\u662f\u4e00\u6a23\u767c\u8457\u5ee2\u6587\u6292\u767c\u60c5\u7dd2\u5462<br /><br />\u5f88\u4e45\u6c92\u6709\u56de\u4f86\u901b\u901b", "images": ["http://filestoresg1.beetalkmobile.com:8081/file/c50da725fb17e67d2cf8689d497940e1"], "urls": [], "title": "\u563f\u563f \u662f\u5426\u904e\u8457\u5dee\u4e0d\u591a\u7684\u65e5\u5b50\u5462"}, "threadStatus": 0, "regionId": 886, "barStatus": 0, "barId": 205, "postBy": {"utc": 1528090892000, "level": 10, "location": "\u5b9c\u862d\u7e23\u00b7\u53f0\u7063", "avatar": "http://filestoresg1.beetalkmobile.com:8081/file/7582544447808262922", "name": "\u5c0f\u8607"}, "id": 8657438}
