{"forum": {"content": "\u4e0d\u6562\u8aaa\u662f\u7f8e\u9b54\u5973.\u53ea\u662f\u89ba\u5f97\u8001\u4e86", "images": ["http://filestoresg1.beetalkmobile.com:8081/file/cd68608559b5be44ef745cb27e97854b", "http://filestoresg1.beetalkmobile.com:8081/file/620e1ca4ba640be8ab9542ed28633144", "http://filestoresg1.beetalkmobile.com:8081/file/e97bf3f8407ddfd58835782ecf09325f", "http://filestoresg1.beetalkmobile.com:8081/file/7977c0c4cf32e20a23aa8211b1da20f1", "http://filestoresg1.beetalkmobile.com:8081/file/d12d5e4f41c2f1c17a1a4b51d64f0e51"], "urls": [], "title": "\u4f86\u737b\u919c\u7684"}, "threadStatus": 1, "regionId": 886, "barStatus": 0, "barId": 782, "postBy": {"utc": 1529429705000, "level": 1, "location": "\u53f0\u7063", "avatar": "http://filestoresg1.beetalkmobile.com:8081/file/-4551779109826770166", "name": "\ud83d\udc95\u7433\ud83d\udc95"}, "id": 8781446}
