{"forum": {"content": "\u54c8\u54c8 \u8a62\u554f\u5404\u4f4d<br />\u6211\u9019\u6a23\u7b97\u662f\u9577\u5f97\u58de\u58de<br />........\u9084\u662f\u9577\u58de\u4e86", "images": ["http://filestoresg1.beetalkmobile.com:8081/file/c1d5dc90121a7cb3e2bf30b96129907d"], "urls": [], "title": "\u9577\u5f97\u58de\u58de\uff1f  \u9084\u662f\u9577\u58de\uff1f"}, "threadStatus": 0, "regionId": 886, "barStatus": 0, "barId": 205, "postBy": {"utc": 1526168517000, "level": 2, "location": "\u9ad8\u96c4\u5e02\u00b7\u53f0\u7063", "avatar": "http://filestoresg1.beetalkmobile.com:8081/file/-6655863950656835164", "name": "\u5e79\u8a71\u738b  \u8077\u696d\u8b1b\u5e79\u8a71"}, "id": 8463567}
