{"forum": {"content": "\u5b78\u7fd2\u4e0d\u540c\u7684\u89c0\u5ff5\uff0c\u624d\u4e0d\u6703\u7259\u9f52\u88ab\u6252\u5149\u90fd\u4e0d\u61c2\u70ba\u4ec0\u9ebc", "images": ["http://filestoresg1.beetalkmobile.com:8081/file/2485cdedfc736b3ed2e84105687d93b9", "http://filestoresg1.beetalkmobile.com:8081/file/50941e0ba45b4d297e091ade874efbf2"], "urls": [], "title": "\u770b\u770b\u65b0\u66f8"}, "threadStatus": 0, "regionId": 886, "barStatus": 0, "barId": 546, "postBy": {"utc": 1524794521000, "level": 1, "location": "\u53f0\u4e2d\u5e02\u00b7\u53f0\u7063", "avatar": "http://filestoresg1.beetalkmobile.com:8081/file/-2455109384971599063", "name": "\u5c45\u5bb6\u6b50\u5df4"}, "id": 8323411}
