{"forum": {"content": "\u611b\u804a\u5929\u7684\u5feb\u627e\u6211 ", "images": ["http://filestoresg1.beetalkmobile.com:8081/file/2dc411aa30a0b529bde89610b6a45df0", "http://filestoresg1.beetalkmobile.com:8081/file/351a0721f3f1147e660c7bd4219e64fe"], "urls": [], "title": "\u6c42\u7a69\u804a"}, "threadStatus": 1, "regionId": 886, "barStatus": 0, "barId": 205, "postBy": {"utc": 1530944623000, "level": 1, "location": "\u53f0\u7063", "avatar": "http://filestoresg1.beetalkmobile.com:8081/file/6647856233590028272", "name": "\u6c88\u66f8\u79be"}, "id": 8931049}
