{"forum": {"content": "\u4e0d\u8981\u518d\u554f\u6211\u53f0\u7063\u597d\u9084\u662f\u65e5\u672c\u597d\u4e86\ud83d\ude02<br />\u5169\u908a\u90fd\u662f\u6211\u6700\u611b\u7684\u5bb6\u9109\ud83d\udc97", "images": ["http://filestoresg1.beetalkmobile.com:8081/file/e4aaed4a2bff36e63853f6637e8742c1", "http://filestoresg1.beetalkmobile.com:8081/file/7868462c196637ff3f5ec1b4556fd935"], "urls": [], "title": "\ud83c\uddf9\ud83c\uddfcx\ud83c\uddef\ud83c\uddf5"}, "threadStatus": 0, "regionId": 886, "barStatus": 0, "barId": 810, "postBy": {"utc": 1523798266000, "level": 3, "location": "\u6843\u5712\u5e02\u00b7\u53f0\u7063", "avatar": "http://filestoresg1.beetalkmobile.com:8081/file/25631816940732930", "name": "\u5c0f\u5a55"}, "id": 8218100}
