{"forum": {"content": "\u5927\u5bb6\u597d<br />\u6211\u60f3\u554f\u9019\u5169\u500b\u5408\u55ce\uff1f<br />\u4e4b\u524d\u6211\u662f\u8ddf\u96d9\u9b5a\uff0c\u73fe\u4efb\u662f\u8655\u5973<br />\u96d9\u9b5a\u6d3b\u6f51<br />\u8655\u5973\u6709\u7a69\u5b9a\u611f<br />\u8acb\u554f\u5927\u5bb6\u610f\u898b", "images": ["http://filestoresg1.beetalkmobile.com:8081/file/904b844bf08eb5fc44bfa228212fc298"], "urls": [], "title": "\u5929\u874e\u7537\u8655\u5973\u5973\u5408\u55ce"}, "threadStatus": 1, "regionId": 886, "barStatus": 0, "barId": 88, "postBy": {"utc": 1524025166000, "level": 0, "location": "\u53f0\u5357\u5e02\u00b7\u53f0\u7063", "avatar": "http://filestoresg1.beetalkmobile.com:8081/file/-4411600166699097729", "name": "\u5149"}, "id": 8240915}
