{"forum": {"content": "\u81ea\u4ee5\u70ba\u662f\u7684\u5927\u53d4\uff0c\u7121\u804a\u7684\u4eba", "images": ["http://filestoresg1.beetalkmobile.com:8081/file/50adef0ae8ea47b15f6bad00b4e1d8df"], "urls": [], "title": "\u6709\u4e9b\u4eba\u5403\u98fd\u592a\u9592\uff0c\u611b\u7ba1\u9592\u4e8b\uff0c\u4e82\u53bb\u65b7\u5b9a\u4e00\u500b\u4eba\uff0c\u662f\u4e0d\u662f\u592a\u7121\u804a\u963f\uff0c\u81ea\u4ee5\u70ba\u662f"}, "threadStatus": 0, "regionId": 886, "barStatus": 0, "barId": 422, "postBy": {"utc": 1525700430000, "level": 1, "location": "", "avatar": "http://filestoresg1.beetalkmobile.com:8081/file/-1374843630530550380", "name": "\u6f54"}, "id": 8416255}
