{"forum": {"content": "\u9047\u5230\u6cd5\u62c9\u5229\u8eca\u968a \u8d85\u6f02\u4eae\u7684 \u958b\u5fc3 \u9a0e\u9a0e\u6a02", "images": ["http://filestoresg1.beetalkmobile.com:8081/file/7fe1f993d19314f5583702107eeb8118", "http://filestoresg1.beetalkmobile.com:8081/file/754488e492113c3356193593c8d26f8c", "http://filestoresg1.beetalkmobile.com:8081/file/dcfbf1e42255063c6c7d06757a0b88ab", "http://filestoresg1.beetalkmobile.com:8081/file/bbcd4ce542d8cf5d35a4aaa27a6d497e", "http://filestoresg1.beetalkmobile.com:8081/file/468749d2954e396f6afe51856bc815a2", "http://filestoresg1.beetalkmobile.com:8081/file/f10be04cbca1b1e41cec1f0d47936099"], "urls": [], "title": "\u5f70\u5316 \u5357\u6295 \u4e00\u65e5\u904a"}, "threadStatus": 0, "regionId": 886, "barStatus": 0, "barId": 722, "postBy": {"utc": 1525539577000, "level": 7, "location": "\u5f70\u5316\u7e23\u00b7\u53f0\u7063", "avatar": "http://filestoresg1.beetalkmobile.com:8081/file/2559866485744897536", "name": "kakan"}, "id": 8400399}
