{"forum": {"content": "\u5feb\u6a02\u661f\u671f\u4e94 \u4f86\u7897\u958b\u80c3\u7684\u8fa3 \u62c9\u9eb5 \u723d\u723d\u723d\u2026\u2026\u7684\u2026\u2026\u5403\u2026\u2026\ud83d\ude04\ud83d\ude04\ud83d\ude04\ud83d\ude04\ud83d\ude04", "images": ["http://filestoresg1.beetalkmobile.com:8081/file/b7c99ff9a3f077be4062eea2c4deca12", "http://filestoresg1.beetalkmobile.com:8081/file/1461df646e557674812e6c12944b5269"], "urls": [], "title": "\u990a\u751f\u5730\u74dc\u8449 \u5e78\u798f\u81ea\u5df1\u4f86\u2026\u2026"}, "threadStatus": 0, "regionId": 886, "barStatus": 0, "barId": 602, "postBy": {"utc": 1529671538000, "level": 10, "location": "\u53f0\u7063", "avatar": "http://filestoresg1.beetalkmobile.com:8081/file/-7106367931020193081", "name": "\u84ee\u79c0"}, "id": 8803951}
