{"forum": {"content": "25\u6b72\u8001\u5927\u53d4<br />\u96a8\u548c\u7684\u500b\u6027<br />\u4e00\u958b\u59cb\u5bb3\u7f9e\u7684\u8981\u547d<br />\u8a8d\u8b58\u5f8c\u7684\u8052\u566a\u7537\u5b50\ud83d\ude25\ud83d\ude25", "images": ["http://filestoresg1.beetalkmobile.com:8081/file/196d9233609623f890df87ffb79618c7"], "urls": [], "title": "\u6162\u71b1"}, "threadStatus": 0, "regionId": 886, "barStatus": 0, "barId": 205, "postBy": {"utc": 1524376285000, "level": 3, "location": "", "avatar": "http://filestoresg1.beetalkmobile.com:8081/file/-6599199517219118335", "name": "\u5c0f\u9054\ud83d\ude4c\ud83c\udffd"}, "id": 8278995}
