{"forum": {"content": "\u6211\u6709\u4e00\u7c3e\u5e7d\u5922\uff0c\u4e0d\u77e5\u8207\u8ab0\u80fd\u5171\uff0c\u591a\u5c11\u79d8\u5bc6\u5728\u5176\u4e2d\uff0c\u6b32\u8a34\u7121\u4eba\u80fd\u61c2\uff0c\u7a97\u5916\u66f4\u6df1\u9732\u91cd\uff0c\u4eca\u591c\u843d\u82b1\u6210\u51a2\uff0c\u6625\u4f86\u6625\u53bb\u805a\u7121\u8e64\uff0c\u5f92\u7559\u4e00\u7c3e\u5e7d\u5922\uff01\u8ab0\u80fd\u89e3\u6211\u60c5\u8877\uff0c\u8ab0\u5c07\u67d4\u60c5\u6df1\u7a2e\uff0c\u82e5\u80fd\u76f8\u77e5\u53c8\u76f8\u9022\uff0c\u5171\u6b64\u4e00\u7c3e\u5e7d\u5922", "images": ["http://filestoresg1.beetalkmobile.com:8081/file/09080150d118b0cc84d2e9c34a1fda06", "http://filestoresg1.beetalkmobile.com:8081/file/9ed91619ecd0dfc042f1e1805f7386d8", "http://filestoresg1.beetalkmobile.com:8081/file/09080150d118b0cc84d2e9c34a1fda06", "http://filestoresg1.beetalkmobile.com:8081/file/76624270e194d9b37e1b2619a29e3689", "http://filestoresg1.beetalkmobile.com:8081/file/526b1050e2b2d8f486e5398addcdfe45", "http://filestoresg1.beetalkmobile.com:8081/file/76624270e194d9b37e1b2619a29e3689"], "urls": [], "title": "\u4e00\u7c3e\u5e7d\u5922"}, "threadStatus": 0, "regionId": 886, "barStatus": 0, "barId": 205, "postBy": {"utc": 1528642028000, "level": 2, "location": "\u65b0\u5317\u5e02\u00b7\u53f0\u7063", "avatar": "http://filestoresg1.beetalkmobile.com:8081/file/2", "name": "User blocked"}, "id": 8710336}
