{"forum": {"content": "\u6211\u523a\u9752\u4f5c\u54c1\u6b23\u8cde (\u90e8\u4efd\u672a\u5b8c\u6210\uff09", "images": ["http://filestoresg1.beetalkmobile.com:8081/file/676eb91d458c48b1aa3d794c1329c140", "http://filestoresg1.beetalkmobile.com:8081/file/a1566f5448cf4e0faf867b0a6a1cacb7", "http://filestoresg1.beetalkmobile.com:8081/file/bf45db3b41d9ec9ff73ccf8cb3ef92af", "http://filestoresg1.beetalkmobile.com:8081/file/a5195d4536f73ee5162b1c081a01f863", "http://filestoresg1.beetalkmobile.com:8081/file/c44cb4e9a4419521995bd3db6b6eb5ce", "http://filestoresg1.beetalkmobile.com:8081/file/3fe3193cc9128c20dfc75bc2db5ef184"], "urls": [], "title": "\u8fd1\u671f\u4f5c\u54c1"}, "threadStatus": 0, "regionId": 886, "barStatus": 0, "barId": 35, "postBy": {"utc": 1528540149000, "level": 6, "location": "\u53f0\u5317\u5e02\u00b7\u53f0\u7063", "avatar": "http://filestoresg1.beetalkmobile.com:8081/file/3826939305232940800", "name": "mai"}, "id": 8700149}
