{"forum": {"content": "\u53ef\u4ee5\u8a8d\u8b58\u5065\u8eab\u597d\u5925\u4f34\u55ce\uff0c\u4e92\u76f8\u6307\u6559\u5b78\u7fd2<br />\u89ba\u5f97\u6700\u8fd1\u6210\u679c\u4e0d\u932f\u54c8\u54c8", "images": ["http://filestoresg1.beetalkmobile.com:8081/file/f23c1821c6df9a9e9c8fbd3d7502f724"], "urls": [], "title": "\u54c8\u56c9\u54c8\u56c9"}, "threadStatus": 0, "regionId": 886, "barStatus": 0, "barId": 719, "postBy": {"utc": 1530381440000, "level": 1, "location": "\u53f0\u5317\u5e02\u00b7\u53f0\u7063", "avatar": "http://filestoresg1.beetalkmobile.com:8081/file/-7929048916084215894", "name": "wespy"}, "id": 8875614}
