{"forum": {"content": "\u5c31\u60f3\u662f\u4e0d\u53ef\u4ee5\u55ce", "images": ["http://filestoresg1.beetalkmobile.com:8081/file/44293c025ae134d6525ab03144c20955"], "urls": [], "title": "\u60f3\u5a5a\u548c\u5fb5\u5a5a"}, "threadStatus": 0, "regionId": 886, "barStatus": 0, "barId": 740, "postBy": {"utc": 1523304416000, "level": 4, "location": "\u9ad8\u96c4\u5e02\u00b7\u53f0\u7063", "avatar": "http://filestoresg1.beetalkmobile.com:8081/file/-6447686793748737619", "name": "\u5b97\u9716"}, "id": 8169004}
