{"forum": {"content": "\u5c4f\u6771\u9ad8\u96c4\u77ed\u9aee\u5973\u5b69\u4f86\u804a\u5929\ud83d\ude18", "images": ["http://filestoresg1.beetalkmobile.com:8081/file/b1f880c8f344fa4357a855c1aad419eb"], "urls": [], "title": "\u77ed\u9aee\u63a7\ud83d\ude0d"}, "threadStatus": 1, "regionId": 886, "barStatus": 0, "barId": 676, "postBy": {"utc": 1525344125000, "level": 1, "location": "", "avatar": "http://filestoresg1.beetalkmobile.com:8081/file/-8098475983002793728", "name": "\u8a8c~"}, "id": 8379316}
