{"forum": {"content": "\u6bcf\u5929\u60f3\u8457\u4eca\u5929\u8981\u6bd4\u6628\u5929\u9032\u6b65", "images": ["http://filestoresg1.beetalkmobile.com:8081/file/3a629f9d15c7a56ea5c7e6d925b8ada5"], "urls": [], "title": "\ud83d\udcaa"}, "threadStatus": 0, "regionId": 886, "barStatus": 0, "barId": 719, "postBy": {"utc": 1522686766000, "level": 1, "location": "\u53f0\u4e2d\u5e02\u00b7\u53f0\u7063", "avatar": "http://filestoresg1.beetalkmobile.com:8081/file/7508257062371289604", "name": "Siang"}, "id": 8105508}
