{"forum": {"content": "\u90fd\u5df2\u7d9318\u4e86\u662f\u9577\u7684\u4e0d\u597d\u770b\u9084\u662f\uff1f\uff1f", "images": ["http://filestoresg1.beetalkmobile.com:8081/file/cf241843280e5d5ad49dae7097bc4484"], "urls": [], "title": "\u6c92\u5973\u53cb"}, "threadStatus": 1, "regionId": 886, "barStatus": 0, "barId": 205, "postBy": {"utc": 1523130991000, "level": 2, "location": "\u65b0\u5317\u5e02\u00b7\u53f0\u7063", "avatar": "http://filestoresg1.beetalkmobile.com:8081/file/-1612835108826621764", "name": "\u5c0f\u5b87\ud83d\udc2f"}, "id": 8151107}
