{"forum": {"content": "\u81ea\u5df1\u731c\u770b\u770b<br /><br /><br />\u6211\u611b\u5f1f\u5f1f\u9084\u662f\u5927\u53d4\ud83d\ude07\ud83d\ude07\ud83d\ude07\ud83d\ude07<br /><br /><br />", "images": ["http://filestoresg1.beetalkmobile.com:8081/file/96c4f3ae4f3b7816711a11c55c58c907", "http://filestoresg1.beetalkmobile.com:8081/file/046c4f1aa20d6a3b94688417eec3665d"], "urls": [], "title": "\u5f1f\u5f1f\u597d\uff0c\u9084\u662f\u5927\u53d4\u597d"}, "threadStatus": 0, "regionId": 886, "barStatus": 0, "barId": 734, "postBy": {"utc": 1530619561000, "level": 4, "location": "\u9ad8\u96c4\u5e02\u00b7\u53f0\u7063", "avatar": "http://filestoresg1.beetalkmobile.com:8081/file/-9147628867037712688", "name": "\ud83d\ude30\ud83d\udc45\u6069\u6069\ud83d\udc45\ud83d\ude01\ud83d\ude01\ud83d\ude01"}, "id": 8898182}
