{"forum": {"content": "\u9ed8\u9ed8\u770b\u59b3\u9060\u53bb<br /><br />\u6211\u53ea\u6562\u50bb\u5728\u539f\u5730<br /><br />\u56e0\u7232\u50b7\u4e0d\u8d77\u4e5f\u73a9\u4e0d\u8d77\u611f\u60c5\u7684\u904a\u6232<br /><br />\u4e0d\u8981\u7d66\u4e86\u5e0c\u671b\u53c8\u7d66\u4e86\u6211\u7d55\u671b", "images": ["http://filestoresg1.beetalkmobile.com:8081/file/4c0f67fe8e7f02fde3e196a3f6084725"], "urls": [], "title": "\u5bc2\u5bde\u55ae\u8eab\u8ab0\u4f86\u8ca0\u8cac"}, "threadStatus": 0, "regionId": 886, "barStatus": 0, "barId": 383, "postBy": {"utc": 1527378399000, "level": 3, "location": "\u53f0\u5317\u5e02\u00b7\u53f0\u7063", "avatar": "http://filestoresg1.beetalkmobile.com:8081/file/5511094240501500933", "name": "\u98f2\u9d06\u6b62\u6e34"}, "id": 8588029}
