{"forum": {"content": "\u91e3\u904a\u6d77\u91e3\u5834", "images": ["http://filestoresg1.beetalkmobile.com:8081/file/2e519399b0cdad9f0a94b753480c707a", "http://filestoresg1.beetalkmobile.com:8081/file/194a133a8f84e83dccf1ff11598c4661", "http://filestoresg1.beetalkmobile.com:8081/file/25d4827022e5d621a4091311cc8dda83", "http://filestoresg1.beetalkmobile.com:8081/file/f8430417afdb214d276d5c93abd61add"], "urls": [], "title": "\u611b\u91e3\u9b5a"}, "threadStatus": 0, "regionId": 886, "barStatus": 0, "barId": 723, "postBy": {"utc": 1529771475000, "level": 15, "location": "", "avatar": "http://filestoresg1.beetalkmobile.com:8081/file/-1917217321666027414", "name": "TERRY\u611b\u91e3\u9b5a"}, "id": 8814758}
