{"forum": {"content": "\u6709\u4e2d\u58e2\u5167\u58e2\u4eba\u8981\u8ddf\u6211\u53bb\u7db2\u5496\u6253\u7d55\u5730\u6216lol\u55ce\ud83d\ude02", "images": ["http://filestoresg1.beetalkmobile.com:8081/file/ff297aa50d7c4701f897b4d902871d60"], "urls": [], "title": "\u5b89\u5b89"}, "threadStatus": 0, "regionId": 886, "barStatus": 0, "barId": 60, "postBy": {"utc": 1531173952000, "level": 1, "location": "\u6843\u5712\u5e02\u00b7\u53f0\u7063", "avatar": "http://filestoresg1.beetalkmobile.com:8081/file/-5857985722076995468", "name": "\ud83d\ude02\u6211\u4eba\u5f88\u597d\u76f8\u8655\ud83d\ude02"}, "id": 8956328}
