{"forum": {"content": "\u90a3\u5e74\u590f\u5929~\u5be7\u975c\u7684\u6d77!", "images": ["http://filestoresg1.beetalkmobile.com:8081/file/f0e004c6ea9d5f66eb85a864e4dbd349", "http://filestoresg1.beetalkmobile.com:8081/file/f85c302f2802e5a58e009688570464c5", "http://filestoresg1.beetalkmobile.com:8081/file/521190091ac422a6457593feea7f8070"], "urls": [], "title": "\u65b0\u6708\u6c99\u7058"}, "threadStatus": 0, "regionId": 886, "barStatus": 0, "barId": 77, "postBy": {"utc": 1525221523000, "level": 7, "location": "\u6843\u5712\u5e02\u00b7\u53f0\u7063", "avatar": "http://filestoresg1.beetalkmobile.com:8081/file/5019000106414053420", "name": "\u84c1\u84c1"}, "id": 8367078}
