{"forum": {"content": "\u8b1d\u8b1d\u4f60\u4e86\u5594\uff01\u5169\u4f4d\u651d\u5f71\u5e2b\u53d4\u53d4\u5011 \u8f9b\u82e6\u4e86", "images": ["http://filestoresg1.beetalkmobile.com:8081/file/4c2f8a29284a1f0082ca2c774a9301ee", "http://filestoresg1.beetalkmobile.com:8081/file/a2b3cfea0ef46096a60d9047f09a7191", "http://filestoresg1.beetalkmobile.com:8081/file/3bea3f0c82cb5d64d9fe91db98d5c4c3", "http://filestoresg1.beetalkmobile.com:8081/file/a0beed96ab8b3bf56e26a8249b51fc43", "http://filestoresg1.beetalkmobile.com:8081/file/3739cd2803835528354525b3fe907c29", "http://filestoresg1.beetalkmobile.com:8081/file/ec3cfd9eaa9bc64f8d21624a32b0c97d"], "urls": [], "title": "\u54c8\u54c8\u54c8\uff5e"}, "threadStatus": 0, "regionId": 886, "barStatus": 0, "barId": 77, "postBy": {"utc": 1522277173000, "level": 1, "location": "\u53f0\u5317\u5e02\u00b7\u53f0\u7063", "avatar": "http://filestoresg1.beetalkmobile.com:8081/file/-5167278038542415319", "name": "Ig\u624d\u56de:yls10261025"}, "id": 8064171}
