{"forum": {"content": "\u5b78\u4eba\u7576\u7db2\u7f8e", "images": ["http://filestoresg1.beetalkmobile.com:8081/file/1fc260809ba007e54f65aa2d1075925f", "http://filestoresg1.beetalkmobile.com:8081/file/40ac7a3367c818f4ce7153ce3f74027c"], "urls": [], "title": "\u9019\u6a23\u6709\u7db2\u5e25\u55ce\u54c8\u54c8\u54c8"}, "threadStatus": 0, "regionId": 886, "barStatus": 0, "barId": 33, "postBy": {"utc": 1528216151000, "level": 2, "location": "\u65b0\u5317\u5e02\u00b7\u53f0\u7063", "avatar": "http://filestoresg1.beetalkmobile.com:8081/file/-6998821397362018810", "name": "Ryan"}, "id": 8670253}
