{"forum": {"content": "\u6709\u8ab0\u53ef\u4ee5\u4f86\u8a8d\u8b58\u4e00\u4e0b\u55ce <br /><br />\u7a81\u7136\u89ba\u5f97\u597d\u908a\u7de3 \ud83d\ude29\ud83d\ude29\ud83d\ude29\ud83d\ude29\ud83d\ude29<br /><br />\u60f3\u627e\u500b\u4eba\u8ac7\u5fc3\u90fd\u6c92\u6709<br /><br />\u9019\u88e1\u6709\u597d\u5fc3\u4eba\u5e36\u6211\u8d70\u55ce\u3002\u54c8\u54c8\u54c8\ud83d\ude04", "images": ["http://filestoresg1.beetalkmobile.com:8081/file/c3c881cf258f25a26495e0f290009bca"], "urls": [], "title": "\u5e0c\u671b\u53ef\u4ee5\u8a8d\u8b58\u804a\u7684\u4f86\u7684\u4eba"}, "threadStatus": 0, "regionId": 886, "barStatus": 0, "barId": 205, "postBy": {"utc": 1529750714000, "level": 1, "location": "", "avatar": "http://filestoresg1.beetalkmobile.com:8081/file/5302232099726314497", "name": "\u716e\u98ef\u7d66\u59b3\u5403"}, "id": 8811749}
