{"forum": {"content": "\u64bf\u4e86\u96bb\u5c0f\u9ed1\u8c93\uff0c\u5927\u7d042\u30013\u500b\u6708\u5927\u5427\uff01<br />\u6709\u4eba\u9858\u610f\u6536\u7de8\u55ce\uff1f\uff1f\uff1f<br />\u633a\u6d3b\u6f51\u7684\uff0c\u4e5f\u7b97\u89aa\u4eba\u3002<br />\uff08\u65b0\u589e\u7167\u72475/22\uff09", "images": ["http://filestoresg1.beetalkmobile.com:8081/file/551b5f228298da31df408257ae236469", "http://filestoresg1.beetalkmobile.com:8081/file/4c2fd4348c79ca5a4bfc406ece9aaa43", "http://filestoresg1.beetalkmobile.com:8081/file/d14628f8c04c47320c328390bd672b6b", "http://filestoresg1.beetalkmobile.com:8081/file/f1b228ce153b11b1c6808c5067fcd75c"], "urls": [], "title": "\u5c0f\u9ed1\u8c93\u6709\u4eba\u8981\u6536\u7de8\u55ce\uff1f"}, "threadStatus": 0, "regionId": 886, "barStatus": 0, "barId": 751, "postBy": {"utc": 1525870956000, "level": 6, "location": "\u53f0\u7063", "avatar": "http://filestoresg1.beetalkmobile.com:8081/file/-7157333611778841794", "name": "Lazy Lucy"}, "id": 8434004}
