{"forum": {"content": "\u62dc\u62dc\u5b8c\u5403\u8349\u82fa\u96ea\u82b1\u51b0", "images": ["http://filestoresg1.beetalkmobile.com:8081/file/540165658e87489d12c2fa8403f62fb3", "http://filestoresg1.beetalkmobile.com:8081/file/996677fd9c88574be497b836b8dea662"], "urls": [], "title": "\u9ad8\u96c4\u5a46\u5a46\u51b0"}, "threadStatus": 0, "regionId": 886, "barStatus": 0, "barId": 676, "postBy": {"utc": 1522908367000, "level": 16, "location": "\u9ad8\u96c4\u5e02\u00b7\u53f0\u7063", "avatar": "http://filestoresg1.beetalkmobile.com:8081/file/-9183297020233546742", "name": "\u222f\u2660wen wen\u2660\u222f"}, "id": 8127024}
