{"forum": {"content": "\u5feb\u9081\u516540\u6b72\u4e86\uff0c\u5b8c\u4e86\ud83d\ude00", "images": ["http://filestoresg1.beetalkmobile.com:8081/file/42a2c35a46f5e73c8fe209e2d108a961"], "urls": [], "title": "\ud83d\ude31\ud83d\ude31\ud83d\ude31"}, "threadStatus": 0, "regionId": 886, "barStatus": 0, "barId": 205, "postBy": {"utc": 1529578777000, "level": 3, "location": "\u53f0\u4e2d\u5e02\u00b7\u53f0\u7063", "avatar": "http://filestoresg1.beetalkmobile.com:8081/file/951647113506210565", "name": "\u6def"}, "id": 8794857}
