{"forum": {"content": "  \u6709\u6c92\u6709\u6843\u5712\u7684\u60f3\u4f86\u8a8d\u8b58\u4e00\u4e0b<br /><br /><br />\u4e0d\u8981\u5bb3\u7f9e", "images": ["http://filestoresg1.beetalkmobile.com:8081/file/e040b19746b3b2ffd9d18767a205a998"], "urls": [], "title": "\u54c8\u54c8\u54c8"}, "threadStatus": 0, "regionId": 886, "barStatus": 0, "barId": 512, "postBy": {"utc": 1530328996000, "level": 1, "location": "\u6843\u5712\u5e02\u00b7\u53f0\u7063", "avatar": "http://filestoresg1.beetalkmobile.com:8081/file/8552093800675604153", "name": "\u7d19\u77ed\u60c5\u9577\ud83d\ude1e"}, "id": 8869385}
