{"forum": {"content": "\u5c0f\u6d0b\u88dd\u51fa\u5e2d\ud83d\udc95", "images": ["http://filestoresg1.beetalkmobile.com:8081/file/43ce30f456c19d06aeabacd0181d3b2a", "http://filestoresg1.beetalkmobile.com:8081/file/0a2f1cffaad4f537b407c954b5581b0a"], "urls": [], "title": "\u4e00\u65e5\u5973\u4f34"}, "threadStatus": 0, "regionId": 886, "barStatus": 0, "barId": 4, "postBy": {"utc": 1522596058000, "level": 5, "location": "", "avatar": "http://filestoresg1.beetalkmobile.com:8081/file/2052980646746183593", "name": "Lydia\ud83c\udf52"}, "id": 8096117}
