{"forum": {"content": "\u8d70\u500b1-2\u5e74\u8981\u7d50\u5a5a\u6709\u4eba\u9858\u610f\u5831\u540d\u55ce", "images": ["http://filestoresg1.beetalkmobile.com:8081/file/2874d36707b3386cd7022ee73bf86f79", "http://filestoresg1.beetalkmobile.com:8081/file/52b2048173be650957678f0189324cdb", "http://filestoresg1.beetalkmobile.com:8081/file/dfdda14ad961b053e5b5713a9468fc5a", "http://filestoresg1.beetalkmobile.com:8081/file/f19aa7cccc1c03ff569d7dacc38e1bda"], "urls": [], "title": "\u8aa0\u5fb5\u7a69\u5b9a\u4ea4\u5f80"}, "threadStatus": 0, "regionId": 886, "barStatus": 0, "barId": 205, "postBy": {"utc": 1522599045000, "level": 16, "location": "", "avatar": "http://filestoresg1.beetalkmobile.com:8081/file/6146615248108456962", "name": "\u9ec3\u9806\u88d5"}, "id": 8096585}
