{"forum": {"content": "\u6709\u4eba\u4eca\u5929\u5728\u9ad4\u5927\u7df4\u821e\u7684\u55ce", "images": [], "urls": [{"url": "https://youtu.be/M92alL2y2aw", "thumbUrl": "https://i.ytimg.com/vi/M92alL2y2aw/maxresdefault.jpg", "description": " ", "title": "2018\u5e745\u670822\u65e5"}], "title": "\u6c42tag"}, "threadStatus": 0, "regionId": 886, "barStatus": 0, "barId": 847, "postBy": {"utc": 1528122361000, "level": 1, "location": "\u53f0\u4e2d\u5e02\u00b7\u53f0\u7063", "avatar": "http://filestoresg1.beetalkmobile.com:8081/file/-6054587218290581361", "name": "wu"}, "id": 8660816}
