{"forum": {"content": "\u611b\u6211\u7684\u4eba\u5c0d\u6211\u7661\u60c5\u4e0d\u6094\u3000<br /><br />\u6211\u537b\u70ba\u6211\u611b\u7684\u4eba\u7518\u5fc3\u4e00\u751f\u50b7\u60b2<br />   <br />\u5728\u4e4e\u7684\u4eba\u59cb\u7d42\u4e0d\u5c0d\u3000<br /><br />\u8ab0\u5c0d\u8ab0\u4e0d\u5fc5\u865b\u507d<br /><br />\u611b\u6211\u7684\u4eba\u70ba\u6211\u4ed8\u51fa\u4e00\u5207\u3000<br /><br />\u6211\u537b\u70ba\u6211\u611b\u7684\u4eba\u6d41\u6dda\u72c2\u4e82\u5fc3\u788e<br />   <br />\u611b\u8207\u88ab\u611b\u540c\u6a23\u53d7\u7f6a\u3000<br /><br />\u70ba\u4ec0\u9ebc\u4e0d\u61c2\u62d2\u7d55\u7661\u60c5\u7684\u5305\u570d", "images": ["http://filestoresg1.beetalkmobile.com:8081/file/b42297ee5a924e94f0acd2f41941fd2a"], "urls": [], "title": "\u611b\u6211\u7684\u4eba\u548c\u6211\u611b\u7684\u4eba/\u88d8\u6d77\u6b63"}, "threadStatus": 0, "regionId": 886, "barStatus": 0, "barId": 775, "postBy": {"utc": 1523511083000, "level": 9, "location": "\u9ad8\u96c4\u5e02\u00b7\u53f0\u7063", "avatar": "http://filestoresg1.beetalkmobile.com:8081/file/-9183297020233546742", "name": "\u222f\u2660wen wen\u2660\u222f"}, "id": 8189470}
