{"forum": {"content": "\u65b0\u4eba\u4f86\u9019Say hi \ud83d\ude02<br />\u5feb\u4f86\u8ddf\u6211\u804a\u804a\u5929\u4e0d\uff1f", "images": ["http://filestoresg1.beetalkmobile.com:8081/file/337f2f17ee183d10a0a1a640d58af053"], "urls": [], "title": "\u54ce\u5537\u6211\u7684\u5abd\u5440\u2764\ufe0f"}, "threadStatus": 0, "regionId": 886, "barStatus": 0, "barId": 32, "postBy": {"utc": 1524610922000, "level": 2, "location": "", "avatar": "http://filestoresg1.beetalkmobile.com:8081/file/5877878136181855771", "name": "NanNan\u2764\ufe0f\u59b9\u5b50\u5728\u54ea\u2753"}, "id": 8304873}
