{"forum": {"content": "\u60f3\u627e\u500b\u771f\u5fc3\u7684\u59ca\u59ca\uff01\uff01\uff01<br /><br />\u9858\u610f\u966a\u804a\u5929\u7684<br /><br />\u5982\u679c\u53ef\u4ee5\u4e5f\u53ef\u4ee5\u627e\u500b\u6a5f\u6703\u7d04\u5403\u500b\u98ef\u4e92\u76f8\u66f4\u52a0\u4e86\u89e3\u5c0d\u65b9\uff01\uff01", "images": ["http://filestoresg1.beetalkmobile.com:8081/file/99291a1050a17da949fee84d63a8fdea", "http://filestoresg1.beetalkmobile.com:8081/file/5e3f86a0aae5ee9e2798eaa7c5bdd373"], "urls": [], "title": "\u60f3\u627e\u500b\u771f\u5fc3\u7684\u59ca\u59ca"}, "threadStatus": 0, "regionId": 886, "barStatus": 0, "barId": 734, "postBy": {"utc": 1531082545000, "level": 1, "location": "\u53f0\u4e2d\u5e02\u00b7\u53f0\u7063", "avatar": "http://filestoresg1.beetalkmobile.com:8081/file/-6422865342445623030", "name": "\u5929\u5929.180cm"}, "id": 8946934}
