{"forum": {"content": "\u662f\u4e0d\u662f\u5f88\u53ef\u611b\uff0c\u53ef\u60dc\u4e0d\u662f\u6211\u7684\u978b\uff0c\u53ea\u662f\u60dc\u7a7f\u62cd\u7167\uff0c\u54c8\u54c8\uff01Dr. Martens\u771f\u7684\u662f\u5f88\u8b9a!", "images": ["http://filestoresg1.beetalkmobile.com:8081/file/4cc5e155f2f23e1c711adbef59a6366f"], "urls": [], "title": "Dr. Martens\u8001\u76ae"}, "threadStatus": 0, "regionId": 886, "barStatus": 0, "barId": 4, "postBy": {"utc": 1531075588000, "level": 4, "location": "\u65b0\u5317\u5e02\u00b7\u53f0\u7063", "avatar": "http://filestoresg1.beetalkmobile.com:8081/file/2865558223083362596", "name": "\u8d70\u53ec\u7cf8\u53ca\u706b\u9801\u767d\u52fa\u5927\u7f8e"}, "id": 8946472}
