{"forum": {"content": "4/27 \u661f\u671f\u4e94\u4e0b\u5348\u4f11\u5047<br /><br />\u6709\u6c92\u6709\u4eba\u4e5f\u6709\u7a7a\u7684\u5440\uff1f<br /><br />\u4f86\u53bb\u5de8\u57ce\u770b\u500b\u96fb\u5f71\u5427\uff01", "images": ["http://filestoresg1.beetalkmobile.com:8081/file/d150a9fcb4b569f6b2b6ebfb5d787b0a"], "urls": [], "title": "\u65b0\u7af9 4/27 \u4e0b\u5348 \u5fa9\u4ec7\u8005\u806f\u76df3"}, "threadStatus": 0, "regionId": 886, "barStatus": 0, "barId": 47, "postBy": {"utc": 1524672733000, "level": 2, "location": "\u65b0\u7af9\u7e23\u00b7\u53f0\u7063", "avatar": "http://filestoresg1.beetalkmobile.com:8081/file/-7737997780765828863", "name": "James"}, "id": 8311956}
