{"forum": {"content": "\u9084\u4e0d\u932f\u770b\u7684\u4e00\u90e8\u9678\u5287\uff5e \u6700\u8fd1\u4e00\u76f4\u5728\u8ffd\uff5e<br />\u5982\u6b4c\u5e2b\u59b9\u771f\u7684\u8d85\u7f8e\u2764\ufe0f<br />\u9084\u6709\u9280\u96ea \u7389\u5e2b\u5144\u5e25\u6b7b \ud83d\ude0d\ud83d\ude0d", "images": ["http://filestoresg1.beetalkmobile.com:8081/file/1113903a56b0f2588ff7c850915c4535"], "urls": [], "title": "\u70c8\u706b\u5982\u6b4c"}, "threadStatus": 1, "regionId": 886, "barStatus": 0, "barId": 50, "postBy": {"utc": 1522897679000, "level": 0, "location": "", "avatar": "http://filestoresg1.beetalkmobile.com:8081/file/6958297820431276896", "name": "\u59a4\u59a4"}, "id": 8125945}
