{"forum": {"content": "\u52a0\u597d\u53cb<br />4200  1911  6586<br />5826  4237  4248<br />9543  1953  9855<br />0648  2973  0631", "images": ["http://filestoresg1.beetalkmobile.com:8081/file/7b49c4cb925fcb8470e78b67ed42fd18", "http://filestoresg1.beetalkmobile.com:8081/file/dd3b7544b7e9eaff7c7aa89d6f003f09", "http://filestoresg1.beetalkmobile.com:8081/file/6c7897506f3b4f9ea3d70cb97bcb6f8f", "http://filestoresg1.beetalkmobile.com:8081/file/ac5327865c29aa7828980b992a3b1e73"], "urls": [], "title": "\u52a0\u597d\u53cb4200  1911  6586\uff0c\n5826  4237  4248\uff0c\n9543  1953  9855\uff0c\n0648  2973  0631"}, "threadStatus": 1, "regionId": 886, "barStatus": 0, "barId": 820, "postBy": {"utc": 1531245634000, "level": 2, "location": "\u65b0\u5317\u5e02\u00b7\u53f0\u7063", "avatar": "http://filestoresg1.beetalkmobile.com:8081/file/8226858264919070951", "name": "\u760b\u68d2\u7403852"}, "id": 8964691}
