{"forum": {"content": "\u592a\u76f8\u4fe1\u4eba\u6027<br /><br />\u662f\u4e00\u4ef6\u5f88\u5371\u96aa\u7684\u4e8b<br /><br />\u614e\u5165", "images": ["http://filestoresg1.beetalkmobile.com:8081/file/c5f0551c5db1486264740ff35096817c"], "urls": [], "title": "\u53c8\u662f\u4e00\u9846\u6d41\u661f\u6b9e\u843d"}, "threadStatus": 1, "regionId": 886, "barStatus": 0, "barId": 707, "postBy": {"utc": 1527486752000, "level": 16, "location": "\u9ad8\u96c4\u5e02\u00b7\u53f0\u7063", "avatar": "http://filestoresg1.beetalkmobile.com:8081/file/-8908003494322592307", "name": "\u9060\u65b9"}, "id": 8598972}
