{"forum": {"content": "\u5df2\u7d93\u770b\u4e86\u6709\u4e9b\u6587\u7ae0<br />\u8981\u689d\u4ef6\u8981\u4ec0\u9ebc\u7684\uff1f<br /><br />\u90a3\u8acb\u554f\u4e7e\u8106\u8cb7\u6a5f\u5668\u4eba\u6bd4\u8f03\u5feb\u4e86<br />\u4f60\u5feb\u6a02\u4ed6\u4e5f\u5feb\u6a02\u54c8\u54c8\u54c8\u6c92\u6709\u4eba<br /><br />\u4ec0\u9ebc\u90fd\u5f88\u53b2\u5bb3\u7684\u8eab\u908a\u6709\u4e00\u500b\u597d\u95a8\u871c\u597d\u670b\u53cb\u5c31\u8a72\u5077\u7b11\u4e86", "images": ["http://filestoresg1.beetalkmobile.com:8081/file/a26579c51ee0b711b0642af1f3fcdcc2"], "urls": [], "title": "\u6c92\u670b\u53cb\u55ce\uff1f"}, "threadStatus": 0, "regionId": 886, "barStatus": 0, "barId": 13, "postBy": {"utc": 1527479982000, "level": 2, "location": "\u53f0\u4e2d\u5e02\u00b7\u53f0\u7063", "avatar": "http://filestoresg1.beetalkmobile.com:8081/file/-5005741067330996536", "name": "\u9ea5\u9999\u6700\u5c0d\u5473"}, "id": 8598238}
