{"forum": {"content": "\u7d05\u71d2\u725b\u8089", "images": ["http://filestoresg1.beetalkmobile.com:8081/file/009cbe2b4d618516ab9b4f415996eed2", "http://filestoresg1.beetalkmobile.com:8081/file/08a891baea70fa8ec48c080ca4c319cf"], "urls": [], "title": "\u660e\u5929\u7684\u6e1b\u80a5\u9910"}, "threadStatus": 0, "regionId": 886, "barStatus": 0, "barId": 838, "postBy": {"utc": 1528715810000, "level": 3, "location": "\u53f0\u4e2d\u5e02\u00b7\u53f0\u7063", "avatar": "http://filestoresg1.beetalkmobile.com:8081/file/-6088739129019550147", "name": "~\u5764~"}, "id": 8716509}
