{"forum": {"content": "83.06.09<br />\u7537\u5973\u4e0d\u9650<br />\u56e0\u8a72\u5f88\u5c11\u4e86\u5594", "images": ["http://filestoresg1.beetalkmobile.com:8081/file/801477bff6e1efd282d3fd5121cbded0"], "urls": [], "title": "\u751f\u65e5\u6709\u540c\u5929\u7684\u561b"}, "threadStatus": 0, "regionId": 886, "barStatus": 0, "barId": 765, "postBy": {"utc": 1528785051000, "level": 1, "location": "\u96f2\u6797\u7e23\u00b7\u53f0\u7063", "avatar": "http://filestoresg1.beetalkmobile.com:8081/file/-8441730295704488178", "name": "\u51f1\u6587"}, "id": 8722449}
