{"forum": {"content": "\u5927\u53d4\u5927\u53d4\u8001\u662f\u8f38\u22ef", "images": ["http://filestoresg1.beetalkmobile.com:8081/file/554f88d8d6fad94551cd4b3bf37d8323", "http://filestoresg1.beetalkmobile.com:8081/file/3e06775ef8dba6e0b0f683ea9ae235b7"], "urls": [], "title": "\u6c92\u4eba\u8981\u7684\u5927\u53d4"}, "threadStatus": 0, "regionId": 886, "barStatus": 0, "barId": 838, "postBy": {"utc": 1529069891000, "level": 3, "location": "", "avatar": "http://filestoresg1.beetalkmobile.com:8081/file/5079005949869548291", "name": "\u4e18\u5c71\u96e8\u8fb0"}, "id": 8746897}
