{"forum": {"content": "\u6211\u597d\u8a0e\u53ad\u81ea\u5df1\uff0c\u8a0e\u53ad\u9019\u6a23\u7684\u6211", "images": ["http://filestoresg1.beetalkmobile.com:8081/file/7091b454ca29a7af4122c38f3d1f88a4", "http://filestoresg1.beetalkmobile.com:8081/file/26e357d5a440d591bce290a73070d576", "http://filestoresg1.beetalkmobile.com:8081/file/1c7174a5f227eb7792d47f599579baba", "http://filestoresg1.beetalkmobile.com:8081/file/c32c083f38ddc9ef18d9aad3de388f80"], "urls": [], "title": "\u6211\u662f\u4e0d\u662f\u4e0d\u597d"}, "threadStatus": 1, "regionId": 886, "barStatus": 0, "barId": 4, "postBy": {"utc": 1522064941000, "level": 3, "location": "\u53f0\u7063", "avatar": "http://filestoresg1.beetalkmobile.com:8081/file/-8731749591307789370", "name": "\u60f3\u4f60\u4e86"}, "id": 8042475}
