{"forum": {"content": "\u591c\u5e97\u65b0\u624b\u6c42\u4eba\u5e36\u7df4 \u6b61\u8fce\u591c\u5e97\u7fa4\u52a0\u52a0\uff01", "images": ["http://filestoresg1.beetalkmobile.com:8081/file/5e5fa295fa1f317d673d766434a0136b"], "urls": [], "title": "\u9ad8\u96c4\u591c\u5e97"}, "threadStatus": 1, "regionId": 886, "barStatus": 0, "barId": 792, "postBy": {"utc": 1526763036000, "level": 1, "location": "\u9ad8\u96c4\u5e02\u00b7\u53f0\u7063", "avatar": "http://filestoresg1.beetalkmobile.com:8081/file/-1239818103330954239", "name": "\u21bb"}, "id": 8524894}
