{"forum": {"content": "\u6211\u662f1\u4f60\u9858\u610f\u75760\u55ce<br />\u8981\u5f97\u76f4\u63a5+\u6211<br />\u9818\u990a\u4ee3\u66ff\u8cfc\u8cb7<br />\u8d85\u904e25\u4e0d\u8981\u53ef\u4ee5\u55ce", "images": ["http://filestoresg1.beetalkmobile.com:8081/file/244e734c4336327d189cf31bd6c3d7ad"], "urls": [], "title": "\u5c31\u6211\u9019\u6a23\u6709\u4eba\u8981\u55ce"}, "threadStatus": 0, "regionId": 886, "barStatus": 0, "barId": 20, "postBy": {"utc": 1527996667000, "level": 2, "location": "\u53f0\u7063", "avatar": "http://filestoresg1.beetalkmobile.com:8081/file/-1994703193617999092", "name": "\u6bdb\u8c93"}, "id": 8648069}
