{"forum": {"content": "\u4f60\u59b3\u5011\u6703\u9858\u610f\u82b1\u5e73\u5e38\u4e94\u500d\u7684\u50f9\u9322\u8cb7\u6a94\u6b21\u66f4\u9ad8\u7684\u9ed1\u5de7\u514b\u529b\u55ce\uff1f\u4f8b\u5982AMEDEI\u6216GODIVA", "images": ["http://filestoresg1.beetalkmobile.com:8081/file/aa7b95809aa692404ba711ae653d1182"], "urls": [], "title": "\u554f\u554f\u984c"}, "threadStatus": 0, "regionId": 886, "barStatus": 0, "barId": 33, "postBy": {"utc": 1525493881000, "level": 8, "location": "", "avatar": "http://filestoresg1.beetalkmobile.com:8081/file/8002510611037509645", "name": "Marin\ud83e\udd94"}, "id": 8394564}
