{"forum": {"content": "\u8207\u95a8\u871c\ud83d\udc6d", "images": ["http://filestoresg1.beetalkmobile.com:8081/file/d022ab781f8bbaf1a6ae88691520cd7e", "http://filestoresg1.beetalkmobile.com:8081/file/98bb1932823ce61db31f16c8a5ec1bd7", "http://filestoresg1.beetalkmobile.com:8081/file/780dd9593e2083f8ccebaf2e4974d7be", "http://filestoresg1.beetalkmobile.com:8081/file/e36124e94e0a76ccf3025c3c2be66fb2", "http://filestoresg1.beetalkmobile.com:8081/file/a7e2063e81a0302e6b4aaff81b5236e3"], "urls": [], "title": "\u9a62\u5b50\u9910\u5ef3"}, "threadStatus": 0, "regionId": 886, "barStatus": 0, "barId": 98, "postBy": {"utc": 1531372240000, "level": 6, "location": "", "avatar": "http://filestoresg1.beetalkmobile.com:8081/file/-1789316621307293144", "name": "\u4e0d\u592a\u7528\u6b64\u7a0b\u5f0f\u804a\u5929\u8acb\u52a0ig\u8b1d\u8b1d"}, "id": 8976450}
