{"forum": {"content": "\u6b61\u8fce\u5594\uff5e", "images": ["http://filestoresg1.beetalkmobile.com:8081/file/d63aaca4890aacc579eb82d6fbe2cdbd", "http://filestoresg1.beetalkmobile.com:8081/file/1db252e7015025f0d691f001938fdeff", "http://filestoresg1.beetalkmobile.com:8081/file/714294f5bc62f072e1767d6271e2b873", "http://filestoresg1.beetalkmobile.com:8081/file/cfa3584b61557e2d324a6c6afb5807d2", "http://filestoresg1.beetalkmobile.com:8081/file/f8ab53e8829a69183ab87aaf90d78ca9"], "urls": [], "title": "\u4f86\u5427\u4f86\u804a\u5929\ud83d\udc4b\ud83d\udc4b"}, "threadStatus": 0, "regionId": 886, "barStatus": 0, "barId": 438, "postBy": {"utc": 1531321260000, "level": 1, "location": "\u53f0\u5317\u5e02\u00b7\u53f0\u7063", "avatar": "http://filestoresg1.beetalkmobile.com:8081/file/-3640646801532137810", "name": "\u5289\u73b3\u8fb0"}, "id": 8971997}
