{"forum": {"content": "\u81ea\u5df1\u722c\u592a\u75db\u82e6\u4e14\u5b64\u55ae<br />\u5e0c\u671b\u627e\u5230\u4e00\u4f4d\u4e3bBOT<br />\u6709\u53ef\u80fd\u4e00\u8d77\u722c\u4e0a\u767d\u91d1<br />MIC\u9ad8EQ\u4e14\u89c0\u5ff5\u597d\u4f73<br />\u7559lD\u6216\u52a0\u597d\u53cb\u50b3\u4fe1\u606f", "images": ["http://filestoresg1.beetalkmobile.com:8081/file/8f79cc232f97b47752562db9cc8f7759"], "urls": [], "title": "S8 \u55ae/\u96d9\u7a4d\u5206 \u9280\u724c"}, "threadStatus": 1, "regionId": 886, "barStatus": 0, "barId": 60, "postBy": {"utc": 1526443192000, "level": 3, "location": "\u53f0\u5317\u5e02\u00b7\u53f0\u7063", "avatar": "http://filestoresg1.beetalkmobile.com:8081/file/9521791990276352", "name": "\u263a\ufe0f"}, "id": 8491716}
