{"forum": {"content": "\u5b9c\u862d", "images": ["http://filestoresg1.beetalkmobile.com:8081/file/df68c5d8d7744e3afd37a870c3cca4fd", "http://filestoresg1.beetalkmobile.com:8081/file/e48bcc7d236ab6bb9fd8da62eab4c151", "http://filestoresg1.beetalkmobile.com:8081/file/46e847fdf70bfb86dfaa526f4cec1413", "http://filestoresg1.beetalkmobile.com:8081/file/4cdb67e3fc7540e8b5b68753388f47a3", "http://filestoresg1.beetalkmobile.com:8081/file/ea9eaa3bf793a7bb462a38564f2cac1e", "http://filestoresg1.beetalkmobile.com:8081/file/b94518aff40f24a3a6a8c208b1dc83ed"], "urls": [], "title": "\u7f8e\u7f8e\u7684\u98a8\u666f"}, "threadStatus": 0, "regionId": 886, "barStatus": 0, "barId": 77, "postBy": {"utc": 1526442193000, "level": 1, "location": "\u4e5d\u9f8d\u00b7\u9999\u6e2f", "avatar": "http://filestoresg1.beetalkmobile.com:8081/file/-3535807269488650977", "name": "\u857e\u857e"}, "id": 8491626}
