{"forum": {"content": "\u722c\u5347\u843d\u5dee\u516b\u767e\u591a\u7c73\uff0c\u4e00\u8def\u76f4\u7dda\u5d29\u58c1\u4ef0\u653b\uff0c\u5c0f\u8fa3\u6912\u5c71\u982d\u3002\u5c55\u671b\u4e0d\u932f\uff0c\u5927\u534a\u500b\u8302\u6797\u5340\u76e1\u6536\u773c\u5e95\u3002", "images": ["http://filestoresg1.beetalkmobile.com:8081/file/622f98f62fb2d767fa3630b0c388ecc1", "http://filestoresg1.beetalkmobile.com:8081/file/dbb564ac738b643a2dacbffed1b7e8d5", "http://filestoresg1.beetalkmobile.com:8081/file/6c9d82e15c873b90ba0a2da0e743fdc1", "http://filestoresg1.beetalkmobile.com:8081/file/6df4a7be553c0f7a4c008798a4ed5817", "http://filestoresg1.beetalkmobile.com:8081/file/9a0c0fc5b234ac6405376904eae3f67a", "http://filestoresg1.beetalkmobile.com:8081/file/3fd46e719cf02688fe383496165afa3f"], "urls": [], "title": "\u9ad8\u96c4\u8302\u6797\u8db3\u6bcd\u5c71"}, "threadStatus": 0, "regionId": 886, "barStatus": 0, "barId": 721, "postBy": {"utc": 1523771950000, "level": 8, "location": "\u53f0\u5357\u5e02\u00b7\u53f0\u7063", "avatar": "http://filestoresg1.beetalkmobile.com:8081/file/-3570355024050308839", "name": "\u718a\u611b\u5c71\u6797"}, "id": 8215237}
