{"forum": {"content": "\u7b2c\u4e00\u6b21\u7df4\u7fd2\u7576model~(\u670b\u53cb\u8981\u7df4\u529f\uff0c\u6211\u8981\u7167\u7247)\uff0c\u9664\u4e86\u53f3\u908a\u81c9\u6bd4\u8f03\u6697\u4e4b\u5916\u9084\u6709\u4ec0\u9ebc\u9700\u8981\u52a0\u5f37\u55ce?p.s~(\u64fa\u7684\u59ff\u52e2\u4e0d\u592a\u7b26\u5408\u4eba\u9ad4\u5de5\u5b78\u554a)", "images": ["http://filestoresg1.beetalkmobile.com:8081/file/310c4530626d06b9513f33ad8619d1b6"], "urls": [], "title": "\u7d20\u4eba\u62cd\u651d\ud83d\ude01"}, "threadStatus": 1, "regionId": 886, "barStatus": 0, "barId": 33, "postBy": {"utc": 1523903033000, "level": 1, "location": "", "avatar": "http://filestoresg1.beetalkmobile.com:8081/file/-6125142867523756456", "name": "183"}, "id": 8229596}
