{"forum": {"content": "\u7b2c\u4e00\u6b21\u770b\u5230YT\u5f71\u7247<br />\u89ba\u5f97\u662f\u4e00\u500b\u883b\u8166\u7684\u89d2\u8272<br />\u6280\u80fd\u5c31\u5e7e\u500b<br />\u7206\u767c\u9ad8<br />\u5c08\u653b\u5f8c\u6392\u800c\u5df2<br />\u653e\u5b8c\u5c31\u8d70\u4eba", "images": ["http://filestoresg1.beetalkmobile.com:8081/file/c9c370b0dfabc1c65af2e6fd1f14f0fc", "http://filestoresg1.beetalkmobile.com:8081/file/8f2b5d67080cf95efd29d76bde435274", "http://filestoresg1.beetalkmobile.com:8081/file/1d28e29023bb94925cedd8a0f956ae13"], "urls": [], "title": "\u9583\u96fb\u4fe0"}, "threadStatus": 1, "regionId": 886, "barStatus": 0, "barId": 841, "postBy": {"utc": 1523877862000, "level": 1, "location": "\u53f0\u4e2d\u5e02\u00b7\u53f0\u7063", "avatar": "http://filestoresg1.beetalkmobile.com:8081/file/-428648982915746237", "name": "\u7280\u5229\u54e5"}, "id": 8226056}
