{"forum": {"content": "\u7b2c\u4e00\u6b21\u505a\u5c31\u6210\u529f\uff0c\u5f88\u6709\u6210\u5c31\u611f\ud83d\ude0b", "images": ["http://filestoresg1.beetalkmobile.com:8081/file/3ba0a61729e2eb7ee7eacea45dd11493", "http://filestoresg1.beetalkmobile.com:8081/file/3bc01b88f836caa3f1ee5789d73ec100"], "urls": [], "title": "\u9ed1\u7cd6\u73cd\u73e0\u9bae\u5976\u8336"}, "threadStatus": 0, "regionId": 886, "barStatus": 0, "barId": 98, "postBy": {"utc": 1521989987000, "level": 8, "location": "\u9ad8\u96c4\u5e02\u00b7\u53f0\u7063", "avatar": "http://filestoresg1.beetalkmobile.com:8081/file/-7887492895357235065", "name": "\u5c31\u662f\ud83d\udc96\u770b\u523a\u9752"}, "id": 8035373}
