{"forum": {"content": "\u627e\u5230\u4e00\u500b\u771f\u5fc3\u7684\u6709\u90a3\u9ebc\u96e3\u22ef", "images": ["http://filestoresg1.beetalkmobile.com:8081/file/20a65686444149eabf28b9c7cd842033"], "urls": [], "title": "159\u9ad8\u4e8c\u751f"}, "threadStatus": 0, "regionId": 886, "barStatus": 0, "barId": 438, "postBy": {"utc": 1525180553000, "level": 2, "location": "\u9ad8\u96c4\u5e02\u00b7\u53f0\u7063", "avatar": "http://filestoresg1.beetalkmobile.com:8081/file/187028046458426895", "name": "\u7433\uff5e"}, "id": 8363138}
