{"forum": {"content": "\u78ba\u5b9aBT\u9084\u6709\u4eba\u5728\u7528\u55ce  \u600e\u9ebc\u90fd\u6c92\u6709\u80fd\u8a8d\u8b58\u7684\u4eba\u52d2", "images": ["http://filestoresg1.beetalkmobile.com:8081/file/63680a24cdf562399f6426655fda5020"], "urls": [], "title": "\u4f86\u8a8d\u8b58\u554a"}, "threadStatus": 0, "regionId": 886, "barStatus": 0, "barId": 205, "postBy": {"utc": 1530768696000, "level": 1, "location": "\u53f0\u5357\u5e02\u00b7\u53f0\u7063", "avatar": "http://filestoresg1.beetalkmobile.com:8081/file/6509588224494011539", "name": "\u4f60\u6572\u9580\u6211\u958b\u9580"}, "id": 8913169}
