{"forum": {"content": "\u5973\u751f\u4e00\u5b9a\u8981\u7a7f\u9732\uff0c\u986f\u5169\u9846\u5976\u624d\u662f\u6f02\u4eae???<br />\u662f\u9019\u5b9a\u7fa9???\u7591\u60d1\ud83e\udd14<br />\u5169\u9846\u5976\u52dd\u904e\u6e05\u79c0\u8277\u9e97\u7684\u5916\u8868???", "images": ["http://filestoresg1.beetalkmobile.com:8081/file/b074963f0bfd0dc21463dc0141b47ccc", "http://filestoresg1.beetalkmobile.com:8081/file/78955877d101f9eacb07c3bb544182f8", "http://filestoresg1.beetalkmobile.com:8081/file/9140ac3bd65323fedaf8a93a6f7a1946", "http://filestoresg1.beetalkmobile.com:8081/file/ba5a05a36e0f61971ec6a6f89aabdc46", "http://filestoresg1.beetalkmobile.com:8081/file/d30431ac1fc6385e9f3b84e15b4fe0a5"], "urls": [], "title": "\u600e\u6a23\u662f\u6f02\u4eae???"}, "threadStatus": 0, "regionId": 886, "barStatus": 0, "barId": 4, "postBy": {"utc": 1525848321000, "level": 3, "location": "", "avatar": "http://filestoresg1.beetalkmobile.com:8081/file/-3869714656424688895", "name": "\u82b8\u82b8"}, "id": 8431294}
