{"forum": {"content": "\u662f\u5927\u53d4\u90fd\u8a72\u770b\u7684\u7247", "images": ["http://filestoresg1.beetalkmobile.com:8081/file/734778f3c96e3d65ee17c1f6d03d17f0", "http://filestoresg1.beetalkmobile.com:8081/file/d68972e99ae67c0c61359e9b92cd9dd1", "http://filestoresg1.beetalkmobile.com:8081/file/63e15119fa7fee8976e6c756b6c6b4c1"], "urls": [], "title": "\u662f\u5927\u53d4\u90fd\u8a72\u770b\u7684\u7247"}, "threadStatus": 0, "regionId": 886, "barStatus": 0, "barId": 838, "postBy": {"utc": 1529114529000, "level": 3, "location": "\u53f0\u5357\u5e02\u00b7\u53f0\u7063", "avatar": "http://filestoresg1.beetalkmobile.com:8081/file/2383380570836898592", "name": "\u808c\u8089\u63a7"}, "id": 8750705}
