{"forum": {"content": "\u5e25\u54e5\uff0c\u4f60\u662f\u4e0d\u662f\u5973\u53cb\u4e0d\u898b\u4e86\uff0c\u5feb\u4f86\u628a\u4ed6\u5e36\u8d70", "images": ["http://filestoresg1.beetalkmobile.com:8081/file/164dd2910c7af2d2c350ca12d588b54f", "http://filestoresg1.beetalkmobile.com:8081/file/e8b553b8aa897f644f5cdc5ebf0afca4", "http://filestoresg1.beetalkmobile.com:8081/file/57b94c83ea57173c841e8b552c14583e", "http://filestoresg1.beetalkmobile.com:8081/file/95997ac0fbe92d655a5a0482dd6c5830"], "urls": [], "title": "\u5fb5\u500b\u597d\u62cc"}, "threadStatus": 1, "regionId": 886, "barStatus": 0, "barId": 383, "postBy": {"utc": 1529834598000, "level": 1, "location": "\u65b0\u5317\u5e02\u00b7\u53f0\u7063", "avatar": "http://filestoresg1.beetalkmobile.com:8081/file/-9209163046986070396", "name": "Alice"}, "id": 8820558}
