{"forum": {"content": "who u think u r  mdfr  please open ur heart dont be so mii<br /> and dont let me see u ok have cute face and so good body<br /> but u  dont have sweet heart ok? choise new man is not first need ok ! fiirst thing  is try add new friend  we dont let u choise  MDFR ", "images": ["http://filestoresg1.beetalkmobile.com:8081/file/3230482f64ee7df1f1f1fe5c4ee8beaf"], "urls": [], "title": "\u50bb\u773c\uff01"}, "threadStatus": 0, "regionId": 886, "barStatus": 0, "barId": 205, "postBy": {"utc": 1526935494000, "level": 8, "location": "\u65b0\u5317\u5e02\u00b7\u53f0\u7063", "avatar": "http://filestoresg1.beetalkmobile.com:8081/file/-3026679532674567610", "name": "\u5c0f\u7576\u5bb6"}, "id": 8542922}
