{"forum": {"content": "\u53ef\u80fd\u56e0\u70ba\u9577\u4e0d\u5927\u7684\u81c9\u8ddf\u8eab\u6750<br />\u6240\u4ee5\u4e5f\u6c92\u6709\u4eba\u60f3\u8ddf\u6211\u4e00\u8d77\u7a69\u5427\ud83d\ude35", "images": ["http://filestoresg1.beetalkmobile.com:8081/file/c1d544f32ec871b49a1dfa5dafee95fb"], "urls": [], "title": "\u6211\u770b\u8d77\u4f86\u50cf\u672a\u6210\u5e74\u55ce\ud83e\udd14"}, "threadStatus": 0, "regionId": 886, "barStatus": 0, "barId": 4, "postBy": {"utc": 1528208887000, "level": 4, "location": "\u65b0\u5317\u5e02\u00b7\u53f0\u7063", "avatar": "http://filestoresg1.beetalkmobile.com:8081/file/-4344543168501287935", "name": "\ud83d\udc3c\u98df\u66fc\u8c46\u9801\ud83d\udc3c"}, "id": 8669050}
