{"forum": {"content": "\u4e0d\u8d70\u83ef\u9e97\u8def\u7dda\uff0c\u9910\u5ef3\u7a7a\u9593\u4e0d\u5927 \u64fa\u98fe\u88dd\u6f62\u662f\u8d70\u61f7\u820a\u8001\u7269\u54c1\u7684\u98a8\u683c\uff0c\u7528\u6599\u5be6\u5728\u800c\u4e14\u8c50\u5bcc\ud83d\udc4d<br />\u800c\u4e14\u83dc\u55ae\u6703\u4e0d\u5b9a\u6642\u66f4\u65b0\u53e3\u5473\u6b50~", "images": ["http://filestoresg1.beetalkmobile.com:8081/file/521d16cc1be2fbfcb0f7983f73f1979d", "http://filestoresg1.beetalkmobile.com:8081/file/64a093099f2504619940d553e5548edb", "http://filestoresg1.beetalkmobile.com:8081/file/d279e901384d133c1d9e27ae6fa49b20", "http://filestoresg1.beetalkmobile.com:8081/file/f025c55da549382cafbab30cc0fddedb", "http://filestoresg1.beetalkmobile.com:8081/file/e23cb89f2d05a78e72babea795a4b8a1", "http://filestoresg1.beetalkmobile.com:8081/file/acae455fd1b14f9ce62bb9d196744da9"], "urls": [], "title": "\u7f8e\u5473\u79c1\u5b85\u6599\u7406-->\u300a  \u5403\u6771\u897f  \u300b"}, "threadStatus": 0, "regionId": 886, "barStatus": 0, "barId": 98, "postBy": {"utc": 1525516614000, "level": 5, "location": "\u53f0\u4e2d\u5e02\u00b7\u53f0\u7063", "avatar": "http://filestoresg1.beetalkmobile.com:8081/file/7958956776507411971", "name": "\u4f69\u4f69\u5152"}, "id": 8397127}
