{"forum": {"content": "\u4eca\u5929\u4ec0\u9ebc\u6642\u5019\u958b\u98ef\uff01", "images": ["http://filestoresg1.beetalkmobile.com:8081/file/7e0c87f2cfe378452822cddc5b979f51", "http://filestoresg1.beetalkmobile.com:8081/file/5650a5ea01d4b8a68d2dd2a9a08afe17", "http://filestoresg1.beetalkmobile.com:8081/file/bb2517424d4a230f2559c51330d79e61", "http://filestoresg1.beetalkmobile.com:8081/file/617b0f246eff7661cf877f62e61e87c4", "http://filestoresg1.beetalkmobile.com:8081/file/0f02096795817c099b6679ca17bf24d3"], "urls": [], "title": "\u53ef\u611b\u6175\u61f6\u8c93"}, "threadStatus": 0, "regionId": 886, "barStatus": 0, "barId": 751, "postBy": {"utc": 1531123723000, "level": 0, "location": "\u53f0\u7063", "avatar": "http://filestoresg1.beetalkmobile.com:8081/file/-6444980904576128545", "name": "\u8303\u7279\u897f"}, "id": 8950453}
