{"forum": {"content": "\u767c\u73fe\u9ad8\u500b\u5b50\u90fd\u5728\u5317\u90e8\u5c45\u591a<br /><br />\u6211\u8a8d\u8b58\u7684\u4eba\u9664\u4e86\u6211\u7684\u5bb6\u4eba\u4ee5\u5916<br /><br />\u53ea\u6709\u4f4f\u570b\u5916\u7684\u670b\u53cb\u624d\u6709180\u4ee5\u4e0a<br /><br />\u5728\u5357\u90e8\u771f\u7684\u5f88\u96e3\u9047\u5230<br /><br />\u66f4\u5225\u8aaa\u5927\u53d4\u4e86.... <br /><br />\u662f\u55ce\uff1f", "images": ["http://filestoresg1.beetalkmobile.com:8081/file/c14e38dae5caa6a168aa215f8de22d99", "http://filestoresg1.beetalkmobile.com:8081/file/1e8506c0737632dd06e02f42ad036bd3", "http://filestoresg1.beetalkmobile.com:8081/file/aead3b981e8224965e4e581c5d41f0eb"], "urls": [], "title": "\u5357\u90e8180\u4ee5\u4e0a\u597d\u5c11"}, "threadStatus": 1, "regionId": 886, "barStatus": 0, "barId": 837, "postBy": {"utc": 1529000592000, "level": 0, "location": "", "avatar": "http://filestoresg1.beetalkmobile.com:8081/file/856913185030251614", "name": "\ud83c\udf80Wild Girl\u2603\ufe0f\ud83c\udde8\ud83c\udded\ud83e\uddc0\ud83c\udf77\ud83e\udd51\ud83c\udf51"}, "id": 8742108}
