{"forum": {"content": "\u660e\u671d \u84ee\u6c60\u5927\u5e2b \u8457\u4f5c<br />\u7531\u4e59\u6027\u6cd5\u5e2b \u4e3b\u8b1b<br />\u6b61\u8fce\u60f3\u89c0\u770b\u5168\u96c6\u8005\u5230<br />www.linhson.org.tw\u5b98\u7db2\u4e0b\u9748\u5c71\u4e16\u754c\u2192\u5176\u5b83\u2192\u611a\u5712\u7cbe\u820d\u4e0b\u89c0\u770b\u5168\u96c6 \u517114\u5802\u8ab2", "images": [], "urls": [{"url": "https://m.youtube.com/watch?v=30m4hqE2JEQ&feature=youtu.be", "thumbUrl": "https://i.ytimg.com/vi/30m4hqE2JEQ/default.jpg", "description": "", "title": "\u7af9\u7a97\u96a8\u7b461-1"}], "title": "\u7af9\u7a97\u96a8\u7b46"}, "threadStatus": 0, "regionId": 886, "barStatus": 0, "barId": 6, "postBy": {"utc": 1522682323000, "level": 6, "location": "\u9ad8\u96c4\u5e02\u00b7\u53f0\u7063", "avatar": "http://filestoresg1.beetalkmobile.com:8081/file/-4196046412146311689", "name": "linhson"}, "id": 8104830}
