{"forum": {"content": "\u5927\u5bb6\u6703\u600e\u9ebc\u642d\u914d\u5462\uff1f", "images": ["http://filestoresg1.beetalkmobile.com:8081/file/dabb692c202bc9847346df1a1db0584f"], "urls": [], "title": "5\u584a\u8cb7\u4e00\u500b\u8001\u516c"}, "threadStatus": 0, "regionId": 886, "barStatus": 0, "barId": 205, "postBy": {"utc": 1524236095000, "level": 3, "location": "", "avatar": "http://filestoresg1.beetalkmobile.com:8081/file/-3524308578534107898", "name": "\u7c21\u55ae\u4f86\u8aaa"}, "id": 8264732}
