{"forum": {"content": "\u5fb5\u9084\u662f\u6253\u932f\u5b57<br />\u4e2d\u6587\u6c92\u6551\u4e86", "images": ["http://filestoresg1.beetalkmobile.com:8081/file/4926c42dec84d188208614941897f43e", "http://filestoresg1.beetalkmobile.com:8081/file/9821639ddb6b9ffeb16ec27fdeb91c0b", "http://filestoresg1.beetalkmobile.com:8081/file/eeb75cca03520ae4aae76f28b892bcce"], "urls": [], "title": "\u51b7\u6c23\u5718"}, "threadStatus": 1, "regionId": 886, "barStatus": 0, "barId": 18, "postBy": {"utc": 1528036691000, "level": 1, "location": "", "avatar": "http://filestoresg1.beetalkmobile.com:8081/file/-7168865272553966759", "name": "FB: \u8303\u51b0\u51b0"}, "id": 8652450}
