{"forum": {"content": "\u611b\u4e00\u500b\u4eba.....\u662f\u4ec0\u9ebc\u611f\u89ba\ud83e\udd14", "images": ["http://filestoresg1.beetalkmobile.com:8081/file/438c1cac453f2cd7ae15d7617287c5c8"], "urls": [], "title": "\u611b\u4e00\u500b\u4eba"}, "threadStatus": 1, "regionId": 886, "barStatus": 0, "barId": 205, "postBy": {"utc": 1527433907000, "level": 4, "location": "", "avatar": "http://filestoresg1.beetalkmobile.com:8081/file/-7259722320654129872", "name": "\u5c0f\u5c0f\u5c0f\u4e38\u5b50"}, "id": 8594426}
