{"forum": {"content": "\u773c\u5152\u8ff7\u6fdb\u4e86 \u90a3\u9152\u5f77\u5f7f\u6709\u9ede\u70c8<br />\u591c\u7a7a\u6688\u7729\u4e86 \u661f\u5152\u624d\u6703\u5f80\u4e0b\u589c<br />\u59b3\u81c9\u9830\u67d3\u4e0a\u4e86\u4e00\u62b9\u7d05<br />\u4e0d\u81ea\u7981 \u8b93\u6211\u5077\u543b\u59b3\u7684\u81c9<br />\u6211\u5fc3\u8df3\u6b64\u523b\u9707\u8033\u6b32\u807e<br />\u8f5f\u9686\u7684 \u662f\u5426\u8ab0\u90fd\u807d\u7684\u898b<br /><br />\u661f\u5152\u589c\u5165\u59b3\u773c\u88e1 \u6211\u770b\u898b\u4e86\u7e41\u661f\u9ede\u9ede<br />\u8b93\u6211\u8ff7\u5931\u5728\u59b3\u773c\u5e95\u661f\u7a7a\u88e1<br />\u5fc3\u5152\u589c\u843d\u59b3\u5fc3\u5e95 \u6211\u770b\u898b\u4e86\u611b\u610f\u7e7e\u7da3<br />\u8b93\u6211\u6dea\u5165\u5728\u59b3\u7de8\u7e54\u60c5\u7db2\u88e1<br />\u6211\u9189\u4e86 <br />\u9189\u5728\u59b3\u773c\u5e95 <br />\u6211\u9189\u5728\u90a3\u7247\u661f\u7a7a\u88e1<br /><br />When I look into your eyes<br />I tend to lose my thoughts<br />                      <br />                                by\u51b0\u5c01\u60e1\u9b54<br /><br /><br /><br />\u5716\u7247\uff1a\u7db2\u8def<br />\u4fee\u6539\uff1a\u51b0\u5c01<br />\u6587\u5b57\uff1a\u51b0\u5c01\ud83d\ude08<br />When I look into your eyes<br />I tend to lose my thoughts<br />\u51fa\u81eaRa Ra Riot/Can You Tell<br />\u4e0d\u932f\u807d<br /><br /><br /><br />", "images": ["http://filestoresg1.beetalkmobile.com:8081/file/9924a3acf20b6f3979452b292452a0a9"], "urls": [], "title": "\u9189\u4e86"}, "threadStatus": 0, "regionId": 886, "barStatus": 0, "barId": 707, "postBy": {"utc": 1525626367000, "level": 16, "location": "\u53f0\u7063", "avatar": "http://filestoresg1.beetalkmobile.com:8081/file/-3866783381826505104", "name": "\u51b0\u5c01\u60e1\u9b54-\u555f\u793a\u9304"}, "id": 8409580}
